odoo/addons/website_snippet_marginless_gallery/README.rst
odoo/addons/website_snippet_marginless_gallery/__init__.py
odoo/addons/website_snippet_marginless_gallery/__manifest__.py
odoo/addons/website_snippet_marginless_gallery/i18n/ca.po
odoo/addons/website_snippet_marginless_gallery/i18n/de.po
odoo/addons/website_snippet_marginless_gallery/i18n/es.po
odoo/addons/website_snippet_marginless_gallery/i18n/fr.po
odoo/addons/website_snippet_marginless_gallery/i18n/it.po
odoo/addons/website_snippet_marginless_gallery/i18n/pt_BR.po
odoo/addons/website_snippet_marginless_gallery/i18n/ru.po
odoo/addons/website_snippet_marginless_gallery/i18n/sl.po
odoo/addons/website_snippet_marginless_gallery/i18n/website_snippet_marginless_gallery.pot
odoo/addons/website_snippet_marginless_gallery/images/marginless_gallery.png
odoo/addons/website_snippet_marginless_gallery/readme/CONTRIBUTORS.md
odoo/addons/website_snippet_marginless_gallery/readme/DESCRIPTION.md
odoo/addons/website_snippet_marginless_gallery/readme/USAGE.md
odoo/addons/website_snippet_marginless_gallery/static/description/icon.png
odoo/addons/website_snippet_marginless_gallery/static/description/icon.svg
odoo/addons/website_snippet_marginless_gallery/static/description/index.html
odoo/addons/website_snippet_marginless_gallery/static/description/s_website_marginless_gallery.png
odoo/addons/website_snippet_marginless_gallery/static/src/tests/tours/website_snippet_marginless_gallery.esm.js
odoo/addons/website_snippet_marginless_gallery/tests/__init__.py
odoo/addons/website_snippet_marginless_gallery/tests/test_ui.py
odoo/addons/website_snippet_marginless_gallery/views/snippets.xml
odoo_addon_website_snippet_marginless_gallery-17.0.1.0.0.3.dist-info/METADATA
odoo_addon_website_snippet_marginless_gallery-17.0.1.0.0.3.dist-info/WHEEL
odoo_addon_website_snippet_marginless_gallery-17.0.1.0.0.3.dist-info/top_level.txt
odoo_addon_website_snippet_marginless_gallery-17.0.1.0.0.3.dist-info/RECORD
