Metadata-Version: 2.1
Name: odoo-addon-website_snippet_marginless_gallery
Version: 17.0.1.0.0.3
Requires-Python: >=3.10
Requires-Dist: odoo>=17.0a,<17.1dev
Summary: Add a snippet to have a marginless image gallery
Home-page: https://github.com/OCA/website
License: LGPL-3
Author: =?utf-8?q?Grupo_ESOC_Ingenier=C3=ADa_de_Servicios=2C_Tecnativa=2C_Odoo_Community_Association_=28OCA=29?=
Author-email: support@odoo-community.org
Classifier: Programming Language :: Python
Classifier: Framework :: Odoo
Classifier: Framework :: Odoo :: 17.0
Classifier: License :: OSI Approved :: GNU Lesser General Public License v3 (LGPLv3)
